{
  "country": "Mauritania",
  "playable": true,
  "id": "949b9690f8154997bacf22ca3bdcb15c",
  "regions": [
    {
      "type": "Polygon",
      "id": "158589381b27410aa7c1b8d93c7ca53c",
      "coordinates": [
        [
          [
            -11.947838565391587,
            16.61139255794201
          ],
          [
            -12.536486528868378,
            14.99750635260339
          ],
          [
            -12.830658331747516,
            15.303691514542948
          ],
          [
            -13.435737677453062,
            16.03938304286619
          ],
          [
            -14.099521450242179,
            16.304302273010492
          ],
          [
            -14.577347581428981,
            16.59826365810281
          ],
          [
            -15.135737270558819,
            16.587282416240782
          ],
          [
            -15.623666144258692,
            16.369337063049812
          ],
          [
            -16.12069007004193,
            16.455662543193384
          ],
          [
            -16.463098110407884,
            16.13503611903846
          ],
          [
            -16.549707810929064,
            16.673892116761962
          ],
          [
            -16.270551723688357,
            17.166962795474873
          ],
          [
            -16.14634741867485,
            18.108481553616656
          ],
          [
            -16.256883307347167,
            19.096715806550307
          ],
          [
            -16.37765112961327,
            19.593817246981985
          ],
          [
            -16.277838100641517,
            20.0925206568147
          ],
          [
            -16.536323614965468,
            20.567866319251493
          ],
          [
            -17.06342322434257,
            20.999752102130827
          ],
          [
            -16.845193650773993,
            21.33332347257488
          ],
          [
            -13.850676487182046,
            21.328542108159066
          ],
          [
            -11.947838565391587,
            16.61139255794201
          ]
        ]
      ]
    },
    {
      "type": "Polygon",
      "id": "2bd5fca523ce4dbc855587e330abadbf",
      "coordinates": [
        [
          [
            -11.947838565391587,
            16.61139255794201
          ],
          [
            -9.54500122934885,
            18.526930507290878
          ],
          [
            -5.514462899770009,
            15.574962662886842
          ],
          [
            -5.537744309908447,
            15.501689764869257
          ],
          [
            -9.55023840985939,
            15.486496893775438
          ],
          [
            -9.700255092802706,
            15.264107367407362
          ],
          [
            -10.086846482778213,
            15.330485744686271
          ],
          [
            -10.650791388379417,
            15.132745876521426
          ],
          [
            -11.349095017939504,
            15.411256008358478
          ],
          [
            -11.666078253617854,
            15.388208319556298
          ],
          [
            -11.834207526079467,
            14.79909699142894
          ],
          [
            -12.170750291380301,
            14.616834214735505
          ],
          [
            -12.536486528868378,
            14.99750635260339
          ],
          [
            -11.947838565391587,
            16.61139255794201
          ]
        ]
      ]
    },
    {
      "type": "Polygon",
      "id": "0b76071965a34a6eab02c1076e872d81",
      "coordinates": [
        [
          [
            -8.766307435837396,
            23.42602773949391
          ],
          [
            -8.658572125880449,
            23.30361870287215
          ],
          [
            -9.409333433043946,
            20.439002990857205
          ],
          [
            -12.964803418742356,
            21.598927206637914
          ],
          [
            -13.118754441774712,
            22.771220201096256
          ],
          [
            -12.874221564169575,
            23.284832261645178
          ],
          [
            -11.937224493853321,
            23.374594224536168
          ],
          [
            -11.940624850199931,
            23.64484887060747
          ],
          [
            -8.766307435837396,
            23.42602773949391
          ]
        ]
      ]
    },
    {
      "type": "Polygon",
      "id": "bbf64e4777dc4c14b4f80581c4a3be3d",
      "coordinates": [
        [
          [
            -13.850676487182046,
            21.328542108159066
          ],
          [
            -12.929101935263532,
            21.327070624267563
          ],
          [
            -12.964803418742356,
            21.598927206637914
          ],
          [
            -9.409333433043946,
            20.439002990857205
          ],
          [
            -9.199626227883394,
            20.022623890463112
          ],
          [
            -9.54500122934885,
            18.526930507290878
          ],
          [
            -11.947838565391587,
            16.61139255794201
          ],
          [
            -13.850676487182046,
            21.328542108159066
          ]
        ]
      ]
    },
    {
      "type": "Polygon",
      "id": "1758251eb1564ef3a1630743d3635905",
      "coordinates": [
        [
          [
            -9.199626227883394,
            20.022623890463112
          ],
          [
            -9.409333433043946,
            20.439002990857205
          ],
          [
            -8.658572125880449,
            23.30361870287215
          ],
          [
            -6.269497247155934,
            23.308740126552745
          ],
          [
            -5.971128709324248,
            20.64083344164763
          ],
          [
            -5.914925467922842,
            20.13823299149047
          ],
          [
            -9.199626227883394,
            20.022623890463112
          ]
        ]
      ]
    },
    {
      "type": "Polygon",
      "id": "8cafadc251dc4fb5809f7018d621801c",
      "coordinates": [
        [
          [
            -8.766307435837396,
            23.42602773949391
          ],
          [
            -11.940624850199931,
            23.64484887060747
          ],
          [
            -11.96941891117116,
            25.933352769468268
          ],
          [
            -9.046622802511362,
            25.886781679109397
          ],
          [
            -8.766307435837396,
            23.42602773949391
          ]
        ]
      ]
    },
    {
      "type": "Polygon",
      "id": "4f4a7df84bcc4563a9c09f86fb1afaad",
      "coordinates": [
        [
          [
            -8.658572125880449,
            23.30361870287215
          ],
          [
            -8.766307435837396,
            23.42602773949391
          ],
          [
            -9.046622802511362,
            25.886781679109397
          ],
          [
            -8.6872936670174,
            25.881056219988906
          ],
          [
            -8.684399786809053,
            27.395744126896005
          ],
          [
            -4.923337368174231,
            24.974574082941
          ],
          [
            -6.453786586930335,
            24.956590684503425
          ],
          [
            -6.269497247155934,
            23.308740126552745
          ],
          [
            -8.658572125880449,
            23.30361870287215
          ]
        ]
      ]
    },
    {
      "type": "Polygon",
      "id": "5c10f0e0f9e34b1d86071a656fc0fa47",
      "coordinates": [
        [
          [
            -9.54500122934885,
            18.526930507290878
          ],
          [
            -9.199626227883394,
            20.022623890463112
          ],
          [
            -5.914925467922842,
            20.13823299149047
          ],
          [
            -5.488522508150439,
            16.325102037007966
          ],
          [
            -5.315277268891933,
            16.20185374599184
          ],
          [
            -5.514462899770009,
            15.574962662886842
          ],
          [
            -9.54500122934885,
            18.526930507290878
          ]
        ]
      ]
    }
  ]
}